codepiper/__init__.py
codepiper/build.py
codepiper/cli.py
codepiper/context.py
codepiper/debug.py
codepiper/pipeline_clear.py
codepiper/rollback.py
codepiper/utils.py
codepiper/watch.py
codepiper-0.2.1.dist-info/LICENSE
codepiper-0.2.1.dist-info/METADATA
codepiper-0.2.1.dist-info/WHEEL
codepiper-0.2.1.dist-info/entry_points.txt
codepiper-0.2.1.dist-info/top_level.txt
codepiper-0.2.1.dist-info/RECORD
