Metadata-Version: 2.1
Name: codepiper
Version: 0.2.1
Summary: Tools for AWS CodePipeline.
Home-page: https://github.com/gaggle-net/codepiper
Author: Gaggle Devops
Author-email: devops@gaggle.net
Classifier: Programming Language :: Python :: 3
Classifier: License :: OSI Approved :: MIT License
Classifier: Operating System :: OS Independent
Requires-Python: ~=3.8
License-File: LICENSE
Requires-Dist: botocore
Requires-Dist: boto3
Requires-Dist: enlighten
